flask_ipblock/__init__.py
flask_ipblock/documents.py
flask_ipblock-0.3.dist-info/DESCRIPTION.rst
flask_ipblock-0.3.dist-info/METADATA
flask_ipblock-0.3.dist-info/RECORD
flask_ipblock-0.3.dist-info/WHEEL
flask_ipblock-0.3.dist-info/metadata.json
flask_ipblock-0.3.dist-info/top_level.txt
