Metadata-Version: 2.0
Name: flask-ipblock
Version: 0.3
Summary: Block certain IP addresses from accessing your Flask app
Home-page: http://github.com/closeio/flask-ipblock
Author: UNKNOWN
Author-email: UNKNOWN
License: MIT
Platform: any
Classifier: Intended Audience :: Developers
Classifier: Operating System :: OS Independent
Classifier: Topic :: Software Development :: Libraries :: Python Modules
Classifier: Programming Language :: Python
Classifier: Programming Language :: Python :: 2
Requires-Dist: Flask
Requires-Dist: mongoengine
